rest_framework_auth0/apps.py
rest_framework_auth0/authentication.py
rest_framework_auth0/decorators.py
rest_framework_auth0/migrations/__init__.py
rest_framework_auth0/models.py
rest_framework_auth0/permissions.py
rest_framework_auth0/serializers.py
rest_framework_auth0/settings.py
rest_framework_auth0/tests.py
rest_framework_auth0/utils.py
rest_framework_auth0/views.py
rest_framework_auth0-0.6.4.dist-info/LICENSE
rest_framework_auth0-0.6.4.dist-info/WHEEL
rest_framework_auth0-0.6.4.dist-info/METADATA
rest_framework_auth0-0.6.4.dist-info/RECORD
