Metadata-Version: 2.1
Name: rest-framework-auth0
Version: 0.6.4
Summary: This library let you to authenticate an specific user on DRF based on the JWT Token returned by Auth0 Javascript libraries.
License: MIT
Author: Marcelo Cueto
Author-email: cueto@live.cl
Requires-Python: >=3.6
Classifier: Development Status :: 4 - Beta
Classifier: Environment :: Web Environment
Classifier: Framework :: Django :: 2.2
Classifier: Framework :: Django :: 3.0
Classifier: Framework :: Django :: 3.1
Classifier: Intended Audience :: Developers
Classifier: Intended Audience :: Information Technology
Classifier: Intended Audience :: System Administrators
Classifier: License :: OSI Approved :: MIT License
Classifier: Operating System :: OS Independent
Classifier: Programming Language :: Python :: 3
Classifier: Programming Language :: Python :: 3.6
Classifier: Programming Language :: Python :: 3.7
Classifier: Programming Language :: Python :: 3.8
Classifier: Programming Language :: Python :: 3.9
Classifier: Topic :: Internet :: WWW/HTTP
Requires-Dist: auth0-python (>=3.12)
Requires-Dist: cryptography (>=3)
Requires-Dist: django (>2.2)
Requires-Dist: pyjwt (>=1.7)
